Metadata-Version: 2.0
Name: django-lorikeet
Version: 0.1.5
Summary: A simple, generic, API-only shopping cart framework for Django
Home-page: UNKNOWN
Author: Adam Brenecki
Author-email: adam@brenecki.id.au
License: MIT
Platform: UNKNOWN
Requires-Dist: django-model-utils (>=2.6,<3)
Requires-Dist: djangorestframework (>=3.5.3,<3.6)
Provides-Extra: docs
Requires-Dist: sphinx (>=1.5.1,<1.6); extra == 'docs'
Requires-Dist: sphinx-js (>=1.3,<1.4); extra == 'docs'
Requires-Dist: sphinx-rtd-theme (>=0.1.9,<0.2); extra == 'docs'
Requires-Dist: sphinxcontrib-httpdomain (>=1.5.0,<2); extra == 'docs'
Provides-Extra: email_invoice
Requires-Dist: premailer (>=3.0.1,<4); extra == 'email_invoice'
Provides-Extra: starshipit
Requires-Dist: requests (<3,>=2.13.0); extra == 'starshipit'
Provides-Extra: stripe
Requires-Dist: stripe (>=1.44.0,<2); extra == 'stripe'
